{
  "effects": [
    {
      "name": "Diffuse",
      "parameters": {
        "diffuse_coeff": 1.100000023841858,
        "iterations": 3.0
      }
    },
    {
      "name": "AudioColor",
      "parameters": {
        "color_coeff": 13.0,
        "mode": 2.0
      }
    },
    {
      "name": "Shadow",
      "parameters": {
        "shadow_coeff": 14.0
      }
    },
    {
      "name": "Diffuse",
      "parameters": {
        "diffuse_coeff": 1.7999999523162842,
        "iterations": 3.0
      }
    }
  ],
  "version": "1.0"
}